{
  "county": "Fresno",
  "page_url": "https://www.fresnocountyca.gov/Services/Adult-Social-Services",
  "link_text": "",
  "program_name_guess": "",
  "nav_path": "",
  "scraped_at": "2026-04-17T13:01:16.094131",
  "registry_signals": [
    "medi-cal"
  ],
  "text": "Adult Services - County of Fresno\nSkip to main content\nopens in new tab or window\nSocial Services\nOpen side\nMenu\nAdult Services\nSub-menu\nAdult Protective Services (APS)\nIn-Home Supportive Services (IHSS)\nFresno County Public Authority\nSub-menu\nIHSS Care Provider Forms\nRequest an IHSS Registry Provider\nWhere is my W-2 ?\nVerify Employment as an IHSS Care Provider\nSecure Document Submission for IHSS & PA\nAssistance Programs\nSub-menu\nApply for Assistance\nCalFresh\nSub-menu\nCalFresh FAQ\nCalWORKs\nSub-menu\nCalWORKs FAQ\nCash Assistance Program for Immigrants (CAPI)\nElectronic Benefit Transfer (EBT) Card Information\nEmployment Services\nChild Care\nNew EBT Cards\nGeneral Relief\nHousing Assistance\nIntercounty Transfers FAQ\nLocations and Services\nMedi-Cal\nSub-menu\nMedi-Cal FAQ\nMinor Consent Medi-Cal\nAged, Blind and Disabled (ABD) Medi-Cal\nHealth Care Options (HCO)\nWelfare to Work Cal-Learn Program\nAssistance Programs for Non-Citizens\nCalFresh Changes\nVeterans Service Office\nDSS Administration\nSub-menu\nNeighborhood Resource Centers\nCivil Rights\nFoster Care Standards and Oversight Committee\nSub-menu\nFoster Care Standards and Oversight Committee Members\nFCSOC Bylaws, Brown Act, Agendas, Minutes & Supporting Documents\nContact FCSOC\nGuidelines for Seeking a Letter of Support\nIHSS Advisory Committee\nReports and Documents\nSpeaker's Bureau\nDSS Assist Media Toolkits\nState/County Hearings\nOur Administration Team\nContact Social Services\nDSS Customer Service Feedback\nDSS Community Events Calendar\nSub-menu\nTogether for Veterans - Monthly Coalition Meeting\nWednesday Contact Center Changes: Automated Services Only\nCaruthers High School Helping Hands Food Pantry\nLaton Community Monthly Pop-up\nAuberry Community Center Monthly Pop-up\nMonthly Medi-Cal Application Assistance Day with HICAP\nButterfly Gardens Monthly Pop-up\nSanger Community Monthly Pop-up\nCrossroads Village Monthly Pop-up\nDSS Finance\nAdult Services\nWelcome to the Department of Social Services (DSS) Adult Services branch web page.\nAdult Services is comprised of several programs that provide services to assist elders and dependent adults living in Fresno County.\nAdult Protective Services (APS)\nHow to report elder/dependent adult abuse, information about the role of APS, resources for mandated reporting and definitions of types of abuse.\nIn-Home Supportive Services (IHSS)\nProvides a general overview of the IHSS program, eligibility requirements and how to apply.\nFresno County Public Authority\nThe Public Authority was established per State mandate to act as Employer of Record for In-Home Supportive Services (IHSS) Care Providers & maintains a Provider Registry to help the IHSS Recipients find Care Providers so they can remain in their home safely and independently.\nSecure Document Submission for IHSS & PA\nUpload documents for IHSS and the Public Authority securely through this link. Users can upload up to 10 documents at a time and receive confirmation with a date & time stamp.\nAdult Protective Services (APS)\nHow to report elder/dependent adult abuse, information about the role of APS, resources for mandated reporting and definitions of types of abuse.\nIHSS Provider Online Enrollment and Orientation\nUsing your home computer, smartphone, or tablet, you can complete all of the required enrollment forms, watch the required orientation videos, and schedule your quick, in-person appointment to provide your ID and Social Security cards to be uploaded into the computer system!\nJoin the IHSS Public Authority Provider Registry\nThe Public Authority Registry is in search of dedicated, trusted, and qualified professionals to join the Registry and to make a positive impact on the lives of our IHSS Recipients.\nResources\nLinks to various agencies and services that may be of assistance to the residents of Fresno County.\nTopics Related to IHSS Payroll\nFresno County In-Home Supportive Services (IHSS) Payroll is dedicated to helping IHSS providers and recipients with a variety of payroll related issues. IHSS Payroll can assist with timesheet issues, payroll-related questions, and employment verification.\nVeterans Service Office\nInformation about all the services available through the VSO for veterans living in Fresno County.\nBack to top",
  "contacts": {
    "phones": [],
    "emails": []
  },
  "pdf_links": [],
  "source_depth": 2,
  "scraper_version": "phase2_enhanced"
}