{
  "county": "San Luis Obispo",
  "page_url": "https://www.slocounty.ca.gov/departments/health-agency/public-health/all-public-health-services/maternal-child-health",
  "link_text": "",
  "program_name_guess": "",
  "nav_path": "",
  "scraped_at": "2026-04-17T13:06:18.399483",
  "registry_signals": [
    "mcah",
    "pat",
    "home visiting",
    "nurse home visiting"
  ],
  "text": "Maternal & Child Health - County of San Luis Obispo\nSkip to main content\nHealth Agency | Public Health\nCounty of San Luis Obispo\nHome\n»\nDepartments\n»\nHealth Agency\n»\nPublic Health\n»\nAll Public Health Services\n»\nMaternal & Child Health\nMaternal & Child Health\nCalifornia Children's Services\nCalifornia Children's Services (CCS) is a statewide program that arranges, directs, and pays for medical care, equipment, and rehabilitation for children and young adults less than 21 years of age who have eligible medical conditions and whose families are unable to pay for all or part of their care. The Public Health Department connects eligible children with doctors, therapists and other trained specialists who know how to care for their special health needs.\nChildhood Lead Poisoning Prevention\nThe Childhood Lead Poisoning Prevention Program provides services to prevent and reduce the harmful effects of lead poisoning among the County of San Luis Obispo children under the age of six, as well as other high-risk children. This includes increasing awareness regarding the hazards of lead exposure, reducing lead exposure, and increasing the number of children assessed and appropriately blood tested for lead poisoning.\nRecognition from Board of Supervisors for Lead Poisoning Prevention Week 2023:\nHealth Care Program for Children in Foster Care\nThe Health Care Program for Children in Foster Care (HCPCFC) is a state-administered, locally operated program. Public health nurses provide expertise in meeting the medical, dental, mental and developmental needs of children and youth in foster care. In collaboration and consultation with social workers and probation officers, public health nurses provide medical and health care case planning; support in obtaining timely health and dental assessments; expedited referrals for medical, dental, mental health and developmental services; education and more. Public health nurses also participate in creating and updating the Health and Education Passport for every child, and provide psychotropic medication monitoring and oversight. See FAQs and the\nprogram brochure\n(\nalso in Spanish\n) for more detail.\nMaternal, Child & Adolescent Health\nMaternal, Child and Adolescent Health (MCAH) promotes the health and well-being of women of childbearing age, infants, children and adolescents who are at increased risk of adverse health outcomes. By virtue of financial, language or cultural barriers, or mental or physical disabilities, MCAH assures access to health promotion and health care services. These activities include community assessment, planning, evaluation, outreach, advocacy, education, training, and policy development. As part of these efforts, MCAH staff participate in the Child Death Review Team (CDRT) to identify potential system failures and inform strategies for future prevention.\nNavigateSLO Resource Guide\nNavigateSLO (NavSLO) is designed to connect parents, children, teens, providers, and everyone in between with local services. Each section contains links and ways to contact local service providers and resources. Some links are to other community resource guides managed by other organizations.\nThese tips for using the NavigateSLO Resource Guide\nwill help you get started with the guide.\nThe Maternal, Child, and Adolescent Health Program maintains NavSLO.\nMedical Therapy Program\nThe Medical Therapy Program (MTP) is a special program within California Children's Services that provides physical, occupational, and medical therapy services for children who are disabled due to neurological or musculoskeletal disorders. A team of licensed therapists provides eligible children with physical therapy, occupational therapy and specialized equipment, such as orthotics/braces, wheelchairs and other assistive devices.\nThis video shares recognition to CCS MTU from SLO Moment at the Board of Supervisors:\nThis video shares one participant's story:\nNurse Home Visiting\nThis service pairs pregnant women and parents of young children with specially trained nurses and family advocates that promote the health and well-being of families in need of support and guidance. The program promotes improved pregnancy outcomes, nurturing parenting skills, positive child health and development, and family self-sufficiency. Services are voluntary and provided in the comfort of the client’s home or location of their choosing.\nPerinatal Substance Use Prevention\nThis Perinatal Substance Use Prevention Program offers education, training, and technical assistance for prenatal care providers in identifying women at risk for substance use, depression, and domestic violence. For those identified as high-risk, we provide comprehensive assessments, education and links to community resources.\nPenny Borenstein, MD, MPH\nHealth Officer/Public Health Director\nDirector of Health Agency | Public Health: Penny Borenstein, MD, MPH, Health Officer/Public Health Director\nContact Us\nFollow us on social media for updates, events, photos and more:",
  "contacts": {
    "phones": [],
    "emails": []
  },
  "pdf_links": [],
  "source_depth": 1,
  "scraper_version": "phase2_enhanced"
}