{
  "county": "Tulare",
  "page_url": "https://tchhsa.org/eng/public-health/maternal-child-and-adolescent-health-mcah-program",
  "link_text": "MCAH landing page",
  "program_name_guess": "",
  "nav_path": "",
  "scraped_at": "2026-04-17T13:01:57.634128",
  "registry_signals": [
    "nfp",
    "mcah",
    "pat",
    "home visiting",
    "nurse-family partnership"
  ],
  "text": "Maternal, Child, and Adolescent Health (MCAH) Program | Health & Human Services Agency\nSkip to main content\nMaternal, Child, and Adolescent Health (MCAH) Program\nWhat is MCAH?\nThe Maternal, Child, and Adolescent Health (MCAH) is a home visiting program that supports the health and well-being of mothers, babies, children, and youth. Our nurses provide culturally responsive one-on-one support through case management, health education, and connections to helpful community resources. We focus on supporting families during pregnancy and after birth, with priority areas that include maternal mental health, breastfeeding support, interconception care, and education to reduce the risk of Sudden Infant Death Syndrome (SIDS). MCAH also helps improve access to health care for women of childbearing age, pregnant and postpartum women, and children and youth with special health care needs. Bilingual nurses are available to support families in English or Spanish, ensuring families receive accessible and supportive care.\nHome Visiting Programs\nPerinatal Wellness Program\nThe Perinatal Wellness Program (PWP) will assign a case manager to a woman who is demonstrating signs/symptoms of perinatal mood and anxiety disorders (PMAD) based on her score on any of the 3 screening tools named below. To qualify for PWP services, a woman must meet the following criteria:\nBe a resident of Tulare County.\nPregnant or less than one year post delivery.\nReceive a score of 12 or greater or (+) on question #10 of the Edinburgh Postnatal Depression Scale (EPDS).\nOR\nReceive a score of 10 or higher of the Patient Health Questionnaire-9 (PHQ-9).\nOR\nReceive a score of 10 or higher on Generalized Anxiety Disorder scale-7 (GAD-7).\nPrenatal Substance Exposure Program\nAny pregnant woman with any of the following factors will be identified as having a baby at risk for alcohol or other drug exposure and will be eligible for referral to the Prenatal Substance Exposure Program (PSEP) if she meets the following criteria:\nIs a resident of Tulare County\nHas had any positive urine drug screen during current pregnancy\nAnd/or client admits substance use or abuse, including prescription drugs and/or alcohol, during current pregnancy.\nHigh-Risk Infant Program\nThe High-Risk Infant Program (HRIP) aids with accessing community early intervention services as well as assistance with accessing medical care through coordination and referrals to deliver desired services to infants and their families. Any child from birth to one year of age is eligible for referral if they meet the following criteria:\nIs a resident of Tulare County\nDiagnosed failure to thrive\nAnd/or developmental delays not identified in the first six months of age and not receiving other case-management.\nCase Management and Disease Investigation for Pregnant Women of Childbearing Age\nIn Tulare County, gonorrhea infection increased in women of childbearing age from an average of 264 cases per year in 2014-2016 to 305 cases in 2022.  In addition, rates of early syphilis among women of childbearing age have increased from 10.7 per 100,000 in 2016 to 51.4 per 100,000 in 2022.  Unfortunately, with the increase of early syphilis rates, there has been a corresponding increase in congenital syphilis.  Tulare County reported 16 cases of congenital syphilis in 2022 while in 2016 the number was less than 7.\nA nurse case manager provides education to women of childbearing age and pregnant women diagnosed with gonorrhea and syphilis. In conjunction with primary care providers, the nurse case manager will ensure women receive appropriate treatment to prevent complication during pregnancy.\nNurse-Family Partnership (NFP)\nThe Nurse-Family Partnership provides first-time expectant mothers with a Public Health Nurse to improve pregnancy outcomes, improve infant health and development, and promote economic self-efficacy of families. Nurses provide support and education to first-time mothers from pregnancy until their child’s 2nd birthday. To qualify for NFP services a woman must meet the following criteria:\nIs pregnant with their first child\nIs less than 28 weeks pregnant\nMeets the income requirements\nIs a resident of Tulare County\nThe NFP Native American Tribal provides Native American individuals who are pregnant are eligible to enroll in NPF with expanded access:\nIs a resident of Tulare County pregnant with their first child\nEligible to enroll anytime during pregnancy, even after 28 weeks\nEligible to enroll with first and subsequent pregnancies\nDoes not have to be federally recognized\nNo income requirements\nDrug-Exposed Infant Program\nThe Drug Exposed Infant Program offers services for infants who were exposed to drugs or alcohol during pregnancy.  The program provides assessments to identify early intervention needs and helps families connect to appropriate health care and support services.\nAny infant or child from birth to one year of age who has one or more of the following risk factors is eligible for referral:\nMust be a resident of Tulare County\nPositive drug screen during prenatal care or at delivery\nPositive infant drug screen\nMaternal admission of substance use or abuse, including prescription drugs or alcohol, during the pregnancy\nResources\nCar Seat Safety Program\nSafe A Sleep Program\nMCAH Referral Form\nNurse-Family Partnership\nContact & Location\nMonday – Thursday\n8:00 a.m. - 5:00 p.m.\nFriday\n8:00 a.m. – 12:00 p.m.\nTelephone:\n(559) 685-2275\nEmail:\n[email protected]\nGoogle Map\nPage Last Updated\nThu, 04/16/2026 - 13:22",
  "contacts": {
    "phones": [
      "(559) 685-2275"
    ],
    "emails": []
  },
  "pdf_links": [
    "https://tcprobation.com/wp-content/uploads/2025/03/Request-to-Seal-Juvenile-Records-JV-595.pdf"
  ],
  "source_depth": 0,
  "scraper_version": "phase2_enhanced"
}